maps4fs/__init__.py
maps4fs/logger.py
maps4fs/generator/__init__.py
maps4fs/generator/config.py
maps4fs/generator/game.py
maps4fs/generator/map.py
maps4fs/generator/monitor.py
maps4fs/generator/qgis.py
maps4fs/generator/settings.py
maps4fs/generator/statistics.py
maps4fs/generator/utils.py
maps4fs/generator/component/__init__.py
maps4fs/generator/component/background.py
maps4fs/generator/component/building.py
maps4fs/generator/component/config.py
maps4fs/generator/component/dem.py
maps4fs/generator/component/grle.py
maps4fs/generator/component/i3d.py
maps4fs/generator/component/layer.py
maps4fs/generator/component/road.py
maps4fs/generator/component/satellite.py
maps4fs/generator/component/texture.py
maps4fs/generator/component/base/__init__.py
maps4fs/generator/component/base/component.py
maps4fs/generator/component/base/component_image.py
maps4fs/generator/component/base/component_mesh.py
maps4fs/generator/component/base/component_xml.py
maps4fs-2.9.62.dist-info/licenses/LICENSE.md
maps4fs-2.9.62.dist-info/METADATA
maps4fs-2.9.62.dist-info/WHEEL
maps4fs-2.9.62.dist-info/top_level.txt
maps4fs-2.9.62.dist-info/RECORD
