Metadata-Version: 2.4
Name: maps4fs
Version: 2.9.62
Summary: Generate map templates for Farming Simulator from real places.
Author-email: iwatkot <iwatkot@gmail.com>
License-Expression: CC-BY-NC-4.0
Project-URL: Homepage, https://github.com/iwatkot/maps4fs
Project-URL: Repository, https://github.com/iwatkot/maps4fs
Keywords: farmingsimulator,fs,farmingsimulator22,farmingsimulator25,fs22,fs25
Classifier: Programming Language :: Python :: 3.11
Classifier: Programming Language :: Python :: 3.12
Classifier: Operating System :: OS Independent
License-File: LICENSE.md
Requires-Dist: opencv-python
Requires-Dist: osmnx>=2.0.0
Requires-Dist: rasterio
Requires-Dist: geopy
Requires-Dist: trimesh<=4.8.2
Requires-Dist: pydantic
Requires-Dist: pygmdl
Requires-Dist: owslib
Requires-Dist: tqdm
Requires-Dist: scipy
Requires-Dist: pydtmdl
Requires-Dist: manifold3d
Requires-Dist: fast-simplification
Dynamic: license-file
